{
    "version": "3.2.3",
    "flags": {},
    "shapes": [
        {
            "label": "rectangle",
            "score": null,
            "points": [
                [
                    1880,
                    850
                ],
                [
                    2179,
                    1048
                ]
            ],
            "group_id": null,
            "description": "",
            "difficult": false,
            "shape_type": "rectangle",
            "flags": {},
            "attributes": {},
            "kie_linking": []
        },
        {
            "label": "rectangle",
            "score": null,
            "points": [
                [
                    758,
                    79
                ],
                [
                    1397,
                    234
                ]
            ],
            "group_id": null,
            "description": "",
            "difficult": false,
            "shape_type": "rectangle",
            "flags": {},
            "attributes": {},
            "kie_linking": []
        },
        {
            "label": "rectangle",
            "score": null,
            "points": [
                [
                    472,
                    823
                ],
                [
                    721,
                    1074
                ]
            ],
            "group_id": null,
            "description": "",
            "difficult": false,
            "shape_type": "rectangle",
            "flags": {},
            "attributes": {},
            "kie_linking": []
        },
        {
            "label": "rectangle",
            "score": null,
            "points": [
                [
                    1091,
                    1069
                ],
                [
                    1339,
                    1198
                ]
            ],
            "group_id": null,
            "description": "",
            "difficult": false,
            "shape_type": "rectangle",
            "flags": {},
            "attributes": {},
            "kie_linking": []
        },
        {
            "label": "rectangle",
            "score": null,
            "points": [
                [
                    1401,
                    479
                ],
                [
                    1645,
                    602
                ]
            ],
            "group_id": null,
            "description": "",
            "difficult": false,
            "shape_type": "rectangle",
            "flags": {},
            "attributes": {},
            "kie_linking": []
        },
        {
            "label": "rectangle",
            "score": null,
            "points": [
                [
                    756,
                    280
                ],
                [
                    1399,
                    431
                ]
            ],
            "group_id": null,
            "description": "",
            "difficult": false,
            "shape_type": "rectangle",
            "flags": {},
            "attributes": {},
            "kie_linking": []
        },
        {
            "label": "circle",
            "score": null,
            "points": [
                [
                    1162,
                    895
                ],
                [
                    1270,
                    998
                ]
            ],
            "group_id": null,
            "description": "",
            "difficult": false,
            "shape_type": "rectangle",
            "flags": {},
            "attributes": {},
            "kie_linking": []
        },
        {
            "label": "circle",
            "score": null,
            "points": [
                [
                    1658,
                    897
                ],
                [
                    1765,
                    1000
                ]
            ],
            "group_id": null,
            "description": "",
            "difficult": false,
            "shape_type": "rectangle",
            "flags": {},
            "attributes": {},
            "kie_linking": []
        },
        {
            "label": "rectangle",
            "score": null,
            "points": [
                [
                    443,
                    1442
                ],
                [
                    1091,
                    1592
                ]
            ],
            "group_id": null,
            "description": "",
            "difficult": false,
            "shape_type": "rectangle",
            "flags": {},
            "attributes": {},
            "kie_linking": []
        },
        {
            "label": "rectangle",
            "score": null,
            "points": [
                [
                    1460,
                    699
                ],
                [
                    1585,
                    827
                ]
            ],
            "group_id": null,
            "description": "",
            "difficult": false,
            "shape_type": "rectangle",
            "flags": {},
            "attributes": {},
            "kie_linking": []
        },
        {
            "label": "rectangle",
            "score": null,
            "points": [
                [
                    449,
                    1244
                ],
                [
                    1086,
                    1396
                ]
            ],
            "group_id": null,
            "description": "",
            "difficult": false,
            "shape_type": "rectangle",
            "flags": {},
            "attributes": {},
            "kie_linking": []
        }
    ],
    "imagePath": "..\\dataset\\1000_images\\[IEEE_IEEE_International_Solid-State_Circuits_Conference_-_San_Francisco,_CA,_USA_(9-13_Feb._2003)]__10.1109_isscc.2003.1234277_page_7_img1.jpg",
    "imageData": null,
    "imageHeight": 1665,
    "imageWidth": 2475
}