{
    "version": "3.2.3",
    "flags": {},
    "shapes": [
        {
            "label": "rectangle",
            "score": null,
            "points": [
                [
                    599,
                    25
                ],
                [
                    711,
                    85
                ]
            ],
            "group_id": null,
            "description": "",
            "difficult": false,
            "shape_type": "rectangle",
            "flags": {},
            "attributes": {},
            "kie_linking": []
        },
        {
            "label": "rectangle",
            "score": null,
            "points": [
                [
                    568,
                    126
                ],
                [
                    743,
                    267
                ]
            ],
            "group_id": null,
            "description": "",
            "difficult": false,
            "shape_type": "rectangle",
            "flags": {},
            "attributes": {},
            "kie_linking": []
        },
        {
            "label": "rectangle",
            "score": null,
            "points": [
                [
                    475,
                    295
                ],
                [
                    521,
                    338
                ]
            ],
            "group_id": null,
            "description": "",
            "difficult": false,
            "shape_type": "rectangle",
            "flags": {},
            "attributes": {},
            "kie_linking": []
        },
        {
            "label": "rectangle",
            "score": null,
            "points": [
                [
                    194,
                    133
                ],
                [
                    371,
                    272
                ]
            ],
            "group_id": null,
            "description": "",
            "difficult": false,
            "shape_type": "rectangle",
            "flags": {},
            "attributes": {},
            "kie_linking": []
        },
        {
            "label": "rectangle",
            "score": null,
            "points": [
                [
                    236,
                    27
                ],
                [
                    345,
                    90
                ]
            ],
            "group_id": null,
            "description": "",
            "difficult": false,
            "shape_type": "rectangle",
            "flags": {},
            "attributes": {},
            "kie_linking": []
        },
        {
            "label": "circle",
            "score": null,
            "points": [
                [
                    131,
                    47
                ],
                [
                    153,
                    71
                ]
            ],
            "group_id": null,
            "description": "",
            "difficult": false,
            "shape_type": "rectangle",
            "flags": {},
            "attributes": {},
            "kie_linking": []
        },
        {
            "label": "circle",
            "score": null,
            "points": [
                [
                    478,
                    41
                ],
                [
                    509,
                    69
                ]
            ],
            "group_id": null,
            "description": "",
            "difficult": false,
            "shape_type": "rectangle",
            "flags": {},
            "attributes": {},
            "kie_linking": []
        }
    ],
    "imagePath": "..\\dataset\\1000_images\\Input-output_stability_of_time-varying_nonlinear_multiloop_feedback_systems__10.1109tac.1974.1100582_10.1109_tac.1974.1100582_page_4_img2.jpg",
    "imageData": null,
    "imageHeight": 348,
    "imageWidth": 997
}